insights_core_messaging-1.2.20.dist-info/licenses/LICENSE
insights_messaging/__init__.py
insights_messaging/__main__.py
insights_messaging/appbuilder.py
insights_messaging/engine.py
insights_messaging/template.py
insights_messaging/consumers/__init__.py
insights_messaging/consumers/cli.py
insights_messaging/consumers/kafka.py
insights_messaging/consumers/rabbitmq.py
insights_messaging/downloaders/__init__.py
insights_messaging/downloaders/httpfs.py
insights_messaging/downloaders/localfs.py
insights_messaging/downloaders/s3.py
insights_messaging/formats/__init__.py
insights_messaging/publishers/__init__.py
insights_messaging/publishers/cli.py
insights_messaging/publishers/rabbitmq.py
insights_messaging/requeuers/__init__.py
insights_messaging/requeuers/kafka.py
insights_messaging/requeuers/rabbitmq.py
insights_messaging/tests/__init__.py
insights_messaging/tests/test_defaulting_template.py
insights_messaging/tests/test_get_logging_config.py
insights_messaging/tests/test_pluggable_engine.py
insights_messaging/tests/test_resolve_variables.py
insights_messaging/utils/__init__.py
insights_messaging/utils/retry.py
insights_messaging/watchers/__init__.py
insights_messaging/watchers/stats.py
insights_core_messaging-1.2.20.dist-info/METADATA
insights_core_messaging-1.2.20.dist-info/WHEEL
insights_core_messaging-1.2.20.dist-info/top_level.txt
insights_core_messaging-1.2.20.dist-info/RECORD
