Metadata-Version: 2.4
Name: insights-core-messaging
Version: 1.2.20
Summary: Messaging service around insights-core.
Home-page: https://github.com/RedHatInsights/insights-core-messaging
License: Apache 2.0
Classifier: Intended Audience :: Developers
Classifier: Natural Language :: English
Classifier: License :: OSI Approved :: Apache Software License
Classifier: Programming Language :: Python
Classifier: Programming Language :: Python :: 3.6
Classifier: Programming Language :: Python :: 3.7
License-File: LICENSE
Requires-Dist: attrs
Requires-Dist: logstash_formatter
Requires-Dist: requests
Requires-Dist: s3fs
Requires-Dist: app-common-python
Requires-Dist: prometheus_client
Requires-Dist: insights-core
Provides-Extra: develop
Requires-Dist: setuptools; extra == "develop"
Requires-Dist: pytest; extra == "develop"
Requires-Dist: twine; extra == "develop"
Requires-Dist: ipython; extra == "develop"
Requires-Dist: wheel; extra == "develop"
Provides-Extra: kafka
Requires-Dist: confluent-kafka; extra == "kafka"
Provides-Extra: rabbitmq
Requires-Dist: pika; extra == "rabbitmq"
Dynamic: classifier
Dynamic: description
Dynamic: description-content-type
Dynamic: home-page
Dynamic: license
Dynamic: license-file
Dynamic: provides-extra
Dynamic: requires-dist
Dynamic: summary
